pycider/__init__.py
pycider/deciders.py
pycider/playground.py
pycider/processes.py
pycider/py.typed
pycider/types.py
pycider/utils.py
pycider-3.0.1.dist-info/METADATA
pycider-3.0.1.dist-info/WHEEL
pycider-3.0.1.dist-info/RECORD
