Metadata-Version: 2.1
Name: pycider
Version: 3.0.1
Summary: Aggregates composition for domain driven design in Python
Home-page: https://github.com/melodyasper/pycider
Keywords: ddd,domain,design,decider,deciders,aggregates,aggregate,composition
Author: Melody Asper
Author-email: melodieasper@gmail.com
Requires-Python: >=3.12,<4.0
Classifier: Programming Language :: Python :: 3
Classifier: Programming Language :: Python :: 3.12
Project-URL: Repository, https://github.com/melodyasper/pycider
